README.md
setup.py
fetchip/__init__.py
fetchip.egg-info/PKG-INFO
fetchip.egg-info/SOURCES.txt
fetchip.egg-info/dependency_links.txt
fetchip.egg-info/requires.txt
fetchip.egg-info/top_level.txt