Metadata-Version: 2.1
Name: fetchip
Version: 1.0
Summary: Get your public IP address and there Details
Home-page: https://www.spyberrys.co.in
Author: lenin Royal
Author-email: leninroyal@outlook.com
License: UNKNOWN
Project-URL: Source, https://github.com/lenin-Tamilspyboy/fetchip
Keywords: ip address
Platform: UNKNOWN
Classifier: Programming Language :: Python
Classifier: Environment :: Plugins
Classifier: Operating System :: OS Independent
Classifier: Intended Audience :: Developers
Classifier: License :: OSI Approved :: MIT License
